AUTHORS.txt
CHANGES.rst
LICENSE.txt
MANIFEST.in
README.rst
setup.py
django_mobile2/__init__.py
django_mobile2/compat.py
django_mobile2/conf.py
django_mobile2/context_processors.py
django_mobile2/loader.py
django_mobile2/middleware.py
django_mobile2/models.py
django_mobile2.egg-info/PKG-INFO
django_mobile2.egg-info/SOURCES.txt
django_mobile2.egg-info/dependency_links.txt
django_mobile2.egg-info/top_level.txt
django_mobile2/cache/__init__.py
django_mobile2/cache/middleware.py